[
    {
        "Directorate":"Directorate For Agriculture & Rural Economy",
        "Merchant Name":"WWW.COVENTRYUNIVERSITY",
        "Merchant Category Description":"Colleges, universities,professional schools & junior colleges",
        "Transaction Date":"23\/03\/2021",
        "Transaction Amount":"£500.00",
        "Final Expense Description":"External training course - fees"
    },
    {
        "Directorate":"Directorate For Agriculture & Rural Economy",
        "Merchant Name":"Livingston Garden Mach",
        "Merchant Category Description":"Lawn and garden supply stores",
        "Transaction Date":"26\/02\/2021",
        "Transaction Amount":"£1,710.92",
        "Final Expense Description":"Farm equipment - maintenance"
    },
    {
        "Directorate":"Directorate For Agriculture & Rural Economy",
        "Merchant Name":"WWW.GARDENMACHINERYDIR",
        "Merchant Category Description":"Lawn and garden supply stores",
        "Transaction Date":"08\/03\/2021",
        "Transaction Amount":"£1,045.00",
        "Final Expense Description":"Farm equipment OR Agricultural supplies"
    },
    {
        "Directorate":"Directorate For Agriculture & Rural Economy",
        "Merchant Name":"Manutan Uk Ltd",
        "Merchant Category Description":"Office, school supply, and stationery stores",
        "Transaction Date":"01\/03\/2021",
        "Transaction Amount":"£936.00",
        "Final Expense Description":"Farm equipment OR Agricultural supplies"
    },
    {
        "Directorate":"Directorate For Agriculture & Rural Economy",
        "Merchant Name":"Harvest Forecast",
        "Merchant Category Description":"Computer software stores",
        "Transaction Date":"30\/03\/2021",
        "Transaction Amount":"£6,734.94",
        "Final Expense Description":"Specialist software"
    },
    {
        "Directorate":"Directorate For Agriculture & Rural Economy",
        "Merchant Name":"WWW.QA.COM",
        "Merchant Category Description":"Schools & educational svc-not elsewhere classified",
        "Transaction Date":"29\/03\/2021",
        "Transaction Amount":"£994.80",
        "Final Expense Description":"Professional licence - fees OR Professional licence - renewal"
    },
    {
        "Directorate":"Directorate For Agriculture & Rural Economy",
        "Merchant Name":"WWW.QA.COM",
        "Merchant Category Description":"Schools & educational svc-not elsewhere classified",
        "Transaction Date":"29\/03\/2021",
        "Transaction Amount":"£2,561.28",
        "Final Expense Description":"Professional licence - fees OR Professional licence - renewal"
    },
    {
        "Directorate":"Directorate For Agriculture & Rural Economy",
        "Merchant Name":"WWW.QA.COM",
        "Merchant Category Description":"Schools & educational svc-not elsewhere classified",
        "Transaction Date":"29\/03\/2021",
        "Transaction Amount":"£1,062.54",
        "Final Expense Description":"External training course - learning material"
    },
    {
        "Directorate":"Directorate For Agriculture & Rural Economy",
        "Merchant Name":"WWW.QA.COM",
        "Merchant Category Description":"Schools & educational svc-not elsewhere classified",
        "Transaction Date":"26\/03\/2021",
        "Transaction Amount":"£1,620.00",
        "Final Expense Description":"Professional licence - fees OR Professional licence - renewal"
    },
    {
        "Directorate":"Directorate For Agriculture & Rural Economy",
        "Merchant Name":"WWW.QA.COM",
        "Merchant Category Description":"Schools & educational svc-not elsewhere classified",
        "Transaction Date":"26\/03\/2021",
        "Transaction Amount":"£1,062.54",
        "Final Expense Description":"Professional licence - fees OR Professional licence - renewal"
    },
    {
        "Directorate":"Directorate For Agriculture & Rural Economy",
        "Merchant Name":"WWW.QA.COM",
        "Merchant Category Description":"Schools & educational svc-not elsewhere classified",
        "Transaction Date":"26\/03\/2021",
        "Transaction Amount":"£2,781.00",
        "Final Expense Description":"Professional licence - fees OR Professional licence - renewal"
    },
    {
        "Directorate":"Directorate For Agriculture & Rural Economy",
        "Merchant Name":"WWW.QA.COM",
        "Merchant Category Description":"Schools & educational svc-not elsewhere classified",
        "Transaction Date":"26\/03\/2021",
        "Transaction Amount":"£691.20",
        "Final Expense Description":"Professional licence - fees OR Professional licence - renewal"
    },
    {
        "Directorate":"Directorate For Agriculture & Rural Economy",
        "Merchant Name":"WWW.QA.COM",
        "Merchant Category Description":"Schools & educational svc-not elsewhere classified",
        "Transaction Date":"26\/03\/2021",
        "Transaction Amount":"£1,854.00",
        "Final Expense Description":"Specialist softwares OR Specialist software - renewal"
    },
    {
        "Directorate":"Directorate For Agriculture & Rural Economy",
        "Merchant Name":"Eb Balife2021",
        "Merchant Category Description":"Business services-not elsewhere classified",
        "Transaction Date":"25\/03\/2021",
        "Transaction Amount":"£1,182.00",
        "Final Expense Description":"External event - fees"
    },
    {
        "Directorate":"Directorate For Agriculture & Rural Economy",
        "Merchant Name":"Eb Balife2021",
        "Merchant Category Description":"Business services-not elsewhere classified",
        "Transaction Date":"25\/03\/2021",
        "Transaction Amount":"£1,379.00",
        "Final Expense Description":"External event - fees"
    },
    {
        "Directorate":"Directorate For Agriculture & Rural Economy",
        "Merchant Name":"WWW.QA.COM",
        "Merchant Category Description":"Schools & educational svc-not elsewhere classified",
        "Transaction Date":"23\/03\/2021",
        "Transaction Amount":"£5,562.00",
        "Final Expense Description":"Professional licence - fees OR Professional licence - renewal"
    },
    {
        "Directorate":"Directorate For Agriculture & Rural Economy",
        "Merchant Name":"Surveymonkey",
        "Merchant Category Description":"Comp programing,data prcsng,intgrtd sys dsgn srvs",
        "Transaction Date":"19\/03\/2021",
        "Transaction Amount":"£900.00",
        "Final Expense Description":"Professional subscription - fees"
    },
    {
        "Directorate":"Directorate For Agriculture & Rural Economy",
        "Merchant Name":"AMAZON.CO.UK MU7ZK6X04",
        "Merchant Category Description":"Direct marketing-other direct marketers\/not elsew.",
        "Transaction Date":"24\/03\/2021",
        "Transaction Amount":"£621.20",
        "Final Expense Description":"Stationery"
    },
    {
        "Directorate":"Directorate For Agriculture & Rural Economy",
        "Merchant Name":"AMAZON.CO.UK MM7FL0SM4",
        "Merchant Category Description":"Direct marketing-other direct marketers\/not elsew.",
        "Transaction Date":"09\/03\/2021",
        "Transaction Amount":"£543.80",
        "Final Expense Description":"Stationery"
    },
    {
        "Directorate":"Directorate For Agriculture & Rural Economy",
        "Merchant Name":"WWW.ARCO.CO.UK",
        "Merchant Category Description":"Industrial supplies not elsewhere classified",
        "Transaction Date":"10\/03\/2021",
        "Transaction Amount":"£1,359.91",
        "Final Expense Description":"Health & safety equipment"
    },
    {
        "Directorate":"Directorate For Agriculture & Rural Economy",
        "Merchant Name":"B B Wear",
        "Merchant Category Description":"Men's and women's clothing stores",
        "Transaction Date":"16\/03\/2021",
        "Transaction Amount":"£2,677.46",
        "Final Expense Description":"Personal protective equipment OR Specialist protective clothing"
    },
    {
        "Directorate":"Directorate For Agriculture & Rural Economy",
        "Merchant Name":"Uv Light Tech Ltd",
        "Merchant Category Description":"Miscellaneous and specialty retail stores",
        "Transaction Date":"05\/03\/2021",
        "Transaction Amount":"£3,215.60",
        "Final Expense Description":"Scientific farm equipment"
    },
    {
        "Directorate":"Directorate For Agriculture & Rural Economy",
        "Merchant Name":"Niab",
        "Merchant Category Description":"Colleges, universities,professional schools & junior colleges",
        "Transaction Date":"09\/03\/2021",
        "Transaction Amount":"£807.17",
        "Final Expense Description":"External training course - learning material"
    },
    {
        "Directorate":"Directorate For Agriculture & Rural Economy",
        "Merchant Name":"Dicksons Of",
        "Merchant Category Description":"Motor vehicle supplies and new parts",
        "Transaction Date":"15\/03\/2021",
        "Transaction Amount":"£726.94",
        "Final Expense Description":"Carpool - Maintance"
    },
    {
        "Directorate":"Directorate For Agriculture & Rural Economy",
        "Merchant Name":"Ao Retail Limited",
        "Merchant Category Description":"Household appliance stores",
        "Transaction Date":"24\/03\/2021",
        "Transaction Amount":"£669.00",
        "Final Expense Description":"Office equipment"
    },
    {
        "Directorate":"Directorate For Agriculture & Rural Economy",
        "Merchant Name":"Gtvisionltd",
        "Merchant Category Description":"Dental\/lab\/med\/ophthalmic hosp equip & supplies",
        "Transaction Date":"05\/03\/2021",
        "Transaction Amount":"£1,293.41",
        "Final Expense Description":"Scientific farm equipment"
    },
    {
        "Directorate":"Directorate For Agriculture & Rural Economy",
        "Merchant Name":"WWW.APSGROUP.CO.UK",
        "Merchant Category Description":"Consulting, management, and public relations svcs",
        "Transaction Date":"16\/03\/2021",
        "Transaction Amount":"£9,316.32",
        "Final Expense Description":"External training course - learning material"
    },
    {
        "Directorate":"Directorate For Agriculture & Rural Economy",
        "Merchant Name":"Anderson Strathern Llp",
        "Merchant Category Description":"Attorneys, legal services",
        "Transaction Date":"05\/03\/2021",
        "Transaction Amount":"£2,160.00",
        "Final Expense Description":"External training course - fees"
    },
    {
        "Directorate":"Directorate For Agriculture & Rural Economy",
        "Merchant Name":"WWW.THELABSTORE.CO.UK",
        "Merchant Category Description":"Dental\/lab\/med\/ophthalmic hosp equip & supplies",
        "Transaction Date":"09\/03\/2021",
        "Transaction Amount":"£2,396.64",
        "Final Expense Description":"Scientific farm equipment"
    },
    {
        "Directorate":"Directorate For Agriculture & Rural Economy",
        "Merchant Name":"Cnes",
        "Merchant Category Description":"Government services-not elsewhere classified",
        "Transaction Date":"12\/03\/2021",
        "Transaction Amount":"£2,310.64",
        "Final Expense Description":"Building - payment charge"
    },
    {
        "Directorate":"Directorate For Agriculture & Rural Economy",
        "Merchant Name":"Omniplex",
        "Merchant Category Description":"Computer software stores",
        "Transaction Date":"30\/03\/2021",
        "Transaction Amount":"£3,118.50",
        "Final Expense Description":"Professional subscription- fees"
    },
    {
        "Directorate":"Directorate For Agriculture & Rural Economy",
        "Merchant Name":"Omniplex",
        "Merchant Category Description":"Computer software stores",
        "Transaction Date":"30\/03\/2021",
        "Transaction Amount":"£3,118.50",
        "Final Expense Description":"Professional subscription- fees"
    },
    {
        "Directorate":"Directorate For Agriculture & Rural Economy",
        "Merchant Name":"Amznmktplace",
        "Merchant Category Description":"Miscellaneous and specialty retail stores",
        "Transaction Date":"17\/03\/2021",
        "Transaction Amount":"£2,571.71",
        "Final Expense Description":"Photogarphic equipment - accessories"
    },
    {
        "Directorate":"Directorate For Agriculture & Rural Economy",
        "Merchant Name":"Kloeckner Metals Uk",
        "Merchant Category Description":"Building materials, lumber stores",
        "Transaction Date":"23\/03\/2021",
        "Transaction Amount":"£832.06",
        "Final Expense Description":"Farm equipment - maintenance"
    },
    {
        "Directorate":"Directorate For Agriculture & Rural Economy",
        "Merchant Name":"Spaldings Limited",
        "Merchant Category Description":"Professional services-not elsewhere classified",
        "Transaction Date":"23\/03\/2021",
        "Transaction Amount":"£665.06",
        "Final Expense Description":"Farm equipment - maintenance"
    },
    {
        "Directorate":"Directorate For Agriculture & Rural Economy",
        "Merchant Name":"Hoggs Of Fife Ts",
        "Merchant Category Description":"Family clothing stores",
        "Transaction Date":"23\/03\/2021",
        "Transaction Amount":"£1,062.90",
        "Final Expense Description":"Personal protective equipment"
    },
    {
        "Directorate":"Directorate For Agriculture & Rural Economy",
        "Merchant Name":"Amznmktplace",
        "Merchant Category Description":"Miscellaneous and specialty retail stores",
        "Transaction Date":"10\/03\/2021",
        "Transaction Amount":"£1,229.94",
        "Final Expense Description":"Office equipment"
    },
    {
        "Directorate":"Directorate For Agriculture & Rural Economy",
        "Merchant Name":"Amznmktplace",
        "Merchant Category Description":"Miscellaneous and specialty retail stores",
        "Transaction Date":"10\/03\/2021",
        "Transaction Amount":"£1,229.94",
        "Final Expense Description":"Office equipment"
    },
    {
        "Directorate":"Directorate For Agriculture & Rural Economy",
        "Merchant Name":"Enterprise Rent-A-Car",
        "Merchant Category Description":"Enterprise Rent-A-Car",
        "Transaction Date":"19\/03\/2021",
        "Transaction Amount":"£542.30",
        "Final Expense Description":"Vehicle hire"
    },
    {
        "Directorate":"Directorate For Chief Economist",
        "Merchant Name":"Https:\/\/Payments.Strat",
        "Merchant Category Description":"Colleges, universities,professional schools & junior colleges",
        "Transaction Date":"09\/03\/2021",
        "Transaction Amount":"£1,500.00",
        "Final Expense Description":"External training course - fees"
    },
    {
        "Directorate":"Directorate For Chief Medical Officer",
        "Merchant Name":"Premiere Conferencing",
        "Merchant Category Description":"Business services-not elsewhere classified",
        "Transaction Date":"22\/03\/2021",
        "Transaction Amount":"£1,030.77",
        "Final Expense Description":"Professional subscription - fees"
    },
    {
        "Directorate":"Directorate For Children & Families",
        "Merchant Name":"Event Carnegie Founda",
        "Merchant Category Description":"Consulting, management, and public relations svcs",
        "Transaction Date":"10\/03\/2021",
        "Transaction Amount":"£2,953.53",
        "Final Expense Description":"External event - fees"
    },
    {
        "Directorate":"Directorate for Communications, Ministerial Support and Facilities",
        "Merchant Name":"Gb Group Plc",
        "Merchant Category Description":"Government services-not elsewhere classified",
        "Transaction Date":"26\/02\/2021",
        "Transaction Amount":"£6,224.40",
        "Final Expense Description":"Building - payment charge"
    },
    {
        "Directorate":"Directorate for Communications, Ministerial Support and Facilities",
        "Merchant Name":"Driver Bubble B.V.",
        "Merchant Category Description":"Automotive parts, accessories stores",
        "Transaction Date":"02\/03\/2021",
        "Transaction Amount":"£2,804.42",
        "Final Expense Description":"Health & safety equipment"
    },
    {
        "Directorate":"Directorate for Communications, Ministerial Support and Facilities",
        "Merchant Name":"Trello.Com, Atlassian",
        "Merchant Category Description":"Computers, computer peripheral equipment, software",
        "Transaction Date":"08\/03\/2021",
        "Transaction Amount":"£1,290.62",
        "Final Expense Description":"Professional subscription - fees"
    },
    {
        "Directorate":"Directorate for Communications, Ministerial Support and Facilities",
        "Merchant Name":"WWW.BOOKMYCOURSE.COM",
        "Merchant Category Description":"Colleges, univ, pro schools, junior colleges",
        "Transaction Date":"25\/03\/2021",
        "Transaction Amount":"£756.00",
        "Final Expense Description":"External training course - fees"
    },
    {
        "Directorate":"Directorate for Communications, Ministerial Support and Facilities",
        "Merchant Name":"WWW.2020.EU.COM",
        "Merchant Category Description":"Business services-not elsewhere classified",
        "Transaction Date":"18\/03\/2021",
        "Transaction Amount":"£4,950.00",
        "Final Expense Description":"External training course - fees"
    },
    {
        "Directorate":"Directorate for Communications, Ministerial Support and Facilities",
        "Merchant Name":"Elite Training",
        "Merchant Category Description":"Comp programing,data prcsng,intgrtd sys dsgn srvs",
        "Transaction Date":"09\/03\/2021",
        "Transaction Amount":"£2,970.00",
        "Final Expense Description":"External training course - fees"
    },
    {
        "Directorate":"Directorate for Communications, Ministerial Support and Facilities",
        "Merchant Name":"Elite Training",
        "Merchant Category Description":"Comp programing,data prcsng,intgrtd sys dsgn srvs",
        "Transaction Date":"09\/03\/2021",
        "Transaction Amount":"£594.00",
        "Final Expense Description":"External training course - fees"
    },
    {
        "Directorate":"Directorate for Communications, Ministerial Support and Facilities",
        "Merchant Name":"Dhl Express(Uk) Lt",
        "Merchant Category Description":"Courier svc-air & ground, freight forwarders",
        "Transaction Date":"26\/03\/2021",
        "Transaction Amount":"£519.80",
        "Final Expense Description":"Postal Services"
    },
    {
        "Directorate":"Directorate for Communications, Ministerial Support and Facilities",
        "Merchant Name":"Mackays Of Dingwal",
        "Merchant Category Description":"Auto & truck dlrs-sales,svc, reprs,prts, & leasing",
        "Transaction Date":"24\/03\/2021",
        "Transaction Amount":"£581.84",
        "Final Expense Description":"Vehicle - maintenance"
    },
    {
        "Directorate":"Directorate for Communications, Ministerial Support and Facilities",
        "Merchant Name":"G B England Garage Ser",
        "Merchant Category Description":"Automotive service shops",
        "Transaction Date":"23\/03\/2021",
        "Transaction Amount":"£2,782.06",
        "Final Expense Description":"Vehicle - maintenance"
    },
    {
        "Directorate":"Directorate for Communications, Ministerial Support and Facilities",
        "Merchant Name":"Macklin Motors",
        "Merchant Category Description":"Auto & truck dlrs-sales,svc, reprs,prts, & leasing",
        "Transaction Date":"23\/03\/2021",
        "Transaction Amount":"£990.30",
        "Final Expense Description":"Vehicle - maintenance"
    },
    {
        "Directorate":"Directorate for Communications, Ministerial Support and Facilities",
        "Merchant Name":"Arnold Clark Ford",
        "Merchant Category Description":"Automobile and truck dealers-(used only)-sales",
        "Transaction Date":"22\/03\/2021",
        "Transaction Amount":"£971.52",
        "Final Expense Description":"Vehicle - maintenance"
    },
    {
        "Directorate":"Directorate for Communications, Ministerial Support and Facilities",
        "Merchant Name":"County Garage",
        "Merchant Category Description":"Automotive service shops",
        "Transaction Date":"10\/03\/2021",
        "Transaction Amount":"£660.98",
        "Final Expense Description":"Vehicle - maintenance"
    },
    {
        "Directorate":"Directorate for Communications, Ministerial Support and Facilities",
        "Merchant Name":"Premiere Conferencing",
        "Merchant Category Description":"Business services-not elsewhere classified",
        "Transaction Date":"18\/03\/2021",
        "Transaction Amount":"£989.33",
        "Final Expense Description":"Professional subscription - fees"
    },
    {
        "Directorate":"Directorate For Community Health & Care",
        "Merchant Name":"Language Line Limited",
        "Merchant Category Description":"Business services-not elsewhere classified",
        "Transaction Date":"19\/03\/2021",
        "Transaction Amount":"£673.03",
        "Final Expense Description":"External consultancy - fees"
    },
    {
        "Directorate":"Directorate For Digital",
        "Merchant Name":"Currys Online",
        "Merchant Category Description":"Electronic sales",
        "Transaction Date":"17\/03\/2021",
        "Transaction Amount":"£1,389.97",
        "Final Expense Description":"IT hardware - specialist equipment"
    },
    {
        "Directorate":"Directorate For Digital",
        "Merchant Name":"AMAZON.CO.UK MM5Q61ND4",
        "Merchant Category Description":"Direct marketing-other direct marketers\/not elsew.",
        "Transaction Date":"26\/02\/2021",
        "Transaction Amount":"£1,203.99",
        "Final Expense Description":"IT hardware - specialist equipment"
    },
    {
        "Directorate":"Directorate For Digital",
        "Merchant Name":"Mural",
        "Merchant Category Description":"Computer software stores",
        "Transaction Date":"24\/03\/2021",
        "Transaction Amount":"£1,077.93",
        "Final Expense Description":"Professional licence - fees OR Professional licence - renewal"
    },
    {
        "Directorate":"Directorate For Digital",
        "Merchant Name":"Aspose Pty Ltd",
        "Merchant Category Description":"Computers, computer peripheral equipment, software",
        "Transaction Date":"15\/03\/2021",
        "Transaction Amount":"£1,854.48",
        "Final Expense Description":"Professional subscription - fees"
    },
    {
        "Directorate":"Directorate For Digital",
        "Merchant Name":"Amznmktplace",
        "Merchant Category Description":"Miscellaneous and specialty retail stores",
        "Transaction Date":"26\/03\/2021",
        "Transaction Amount":"£1,079.94",
        "Final Expense Description":"Office Equipment"
    },
    {
        "Directorate":"Directorate For Digital",
        "Merchant Name":"WWW.PCWB.COM",
        "Merchant Category Description":"Computer software stores",
        "Transaction Date":"22\/03\/2021",
        "Transaction Amount":"£1,181.95",
        "Final Expense Description":"IT hardware - specialist equipment"
    },
    {
        "Directorate":"Directorate For Digital",
        "Merchant Name":"Blancco Uk Ltd",
        "Merchant Category Description":"Computer software stores",
        "Transaction Date":"15\/03\/2021",
        "Transaction Amount":"£4,864.50",
        "Final Expense Description":"IT hardware - specialist equipment"
    },
    {
        "Directorate":"Directorate For Digital",
        "Merchant Name":"Mural",
        "Merchant Category Description":"Computer software stores",
        "Transaction Date":"11\/03\/2021",
        "Transaction Amount":"£971.61",
        "Final Expense Description":"Professional licence - fees OR Professional licence - renewal"
    },
    {
        "Directorate":"Directorate For Digital",
        "Merchant Name":"Purplegriffon.Com",
        "Merchant Category Description":"Schools & educational svc-not elsewhere classified",
        "Transaction Date":"09\/03\/2021",
        "Transaction Amount":"£1,368.00",
        "Final Expense Description":"External training course - fees"
    },
    {
        "Directorate":"Directorate For Digital",
        "Merchant Name":"Slingsby",
        "Merchant Category Description":"Office and commercial furniture",
        "Transaction Date":"02\/03\/2021",
        "Transaction Amount":"£3,944.11",
        "Final Expense Description":"Office Equipment"
    },
    {
        "Directorate":"Directorate For Digital",
        "Merchant Name":"Colessio Hotel",
        "Merchant Category Description":"Lodging-hotels,motels,resorts-not classified",
        "Transaction Date":"24\/03\/2021",
        "Transaction Amount":"£970.00",
        "Final Expense Description":"External event - fees"
    },
    {
        "Directorate":"Directorate For Digital",
        "Merchant Name":"Watson Martin Partners",
        "Merchant Category Description":"Schools, trade and vocational",
        "Transaction Date":"18\/03\/2021",
        "Transaction Amount":"£8,084.40",
        "Final Expense Description":"External training course - fees"
    },
    {
        "Directorate":"Directorate For Digital",
        "Merchant Name":"WWW.QA.COM",
        "Merchant Category Description":"Schools & educational svc-not elsewhere classified",
        "Transaction Date":"09\/03\/2021",
        "Transaction Amount":"£2,333.04",
        "Final Expense Description":"External training course - fees"
    },
    {
        "Directorate":"Directorate For Digital",
        "Merchant Name":"Amazon Web Services",
        "Merchant Category Description":"Business services-not elsewhere classified",
        "Transaction Date":"13\/03\/2021",
        "Transaction Amount":"£2,210.65",
        "Final Expense Description":"Professional subscription - fees"
    },
    {
        "Directorate":"Directorate For Digital",
        "Merchant Name":"Enterprise Rent-A-Car",
        "Merchant Category Description":"Enterprise Rent-A-Car",
        "Transaction Date":"30\/03\/2021",
        "Transaction Amount":"£1,154.15",
        "Final Expense Description":"Vehicle hire"
    },
    {
        "Directorate":"Directorate For Digital",
        "Merchant Name":"Enterprise Rent-A-Car",
        "Merchant Category Description":"Enterprise Rent-A-Car",
        "Transaction Date":"01\/03\/2021",
        "Transaction Amount":"£1,154.15",
        "Final Expense Description":"Vehicle hire"
    },
    {
        "Directorate":"Directorate For Environment & Forestry",
        "Merchant Name":"Capita Business Servs",
        "Merchant Category Description":"Government services-not elsewhere classified",
        "Transaction Date":"10\/03\/2021",
        "Transaction Amount":"£834.22",
        "Final Expense Description":"External training course - fees"
    },
    {
        "Directorate":"Directorate For Environment & Forestry",
        "Merchant Name":"Tableau",
        "Merchant Category Description":"Consulting, management, and public relations svcs",
        "Transaction Date":"29\/03\/2021",
        "Transaction Amount":"£11,528.53",
        "Final Expense Description":"Professional licence - fees OR Professional licence - renewal"
    },
    {
        "Directorate":"Directorate For External Affairs",
        "Merchant Name":"Rachel_Lothian",
        "Merchant Category Description":"Professional services-not elsewhere classified",
        "Transaction Date":"29\/03\/2021",
        "Transaction Amount":"£650.00",
        "Final Expense Description":"External event - catering costs - (location)"
    },
    {
        "Directorate":"Directorate For External Affairs",
        "Merchant Name":"Click A Courier",
        "Merchant Category Description":"Courier svc-air & ground, freight forwarders",
        "Transaction Date":"16\/03\/2021",
        "Transaction Amount":"£1,786.13",
        "Final Expense Description":"Postal fees"
    },
    {
        "Directorate":"Directorate For External Affairs",
        "Merchant Name":"Sq Glasgow Distillery",
        "Merchant Category Description":"Misc food store-convenience,mrkt,splty,vendng macs",
        "Transaction Date":"11\/03\/2021",
        "Transaction Amount":"£594.00",
        "Final Expense Description":"External event - catering costs - (location)"
    },
    {
        "Directorate":"Directorate For External Affairs",
        "Merchant Name":"Uzr Digistore24 Gmbhhi",
        "Merchant Category Description":"Digital goods audiovisual media",
        "Transaction Date":"24\/03\/2021",
        "Transaction Amount":"£738.25",
        "Final Expense Description":"Professional subscription - fees"
    },
    {
        "Directorate":"Directorate For External Affairs",
        "Merchant Name":"Bccg E.V.",
        "Merchant Category Description":"Organizations, membership-not elsewhere classified",
        "Transaction Date":"17\/03\/2021",
        "Transaction Amount":"£1,512.11",
        "Final Expense Description":"Professional membership - fees OR Professional subscription - fees"
    },
    {
        "Directorate":"Directorate For External Affairs",
        "Merchant Name":"Sq Keepcup Ltd",
        "Merchant Category Description":"Miscellaneous general merchandise",
        "Transaction Date":"29\/03\/2021",
        "Transaction Amount":"£540.52",
        "Final Expense Description":"External event - promotional material OR External event - material"
    },
    {
        "Directorate":"Directorate For External Affairs",
        "Merchant Name":"Www.Ecossegourmet.Fr",
        "Merchant Category Description":"Comp programing,data prcsng,intgrtd sys dsgn srvs",
        "Transaction Date":"19\/03\/2021",
        "Transaction Amount":"£2,243.34",
        "Final Expense Description":"External event - catering costs - (location)"
    },
    {
        "Directorate":"Directorate For External Affairs",
        "Merchant Name":"Arbikiedist",
        "Merchant Category Description":"Package stores, beer, wine, liquor",
        "Transaction Date":"10\/03\/2021",
        "Transaction Amount":"£516.00",
        "Final Expense Description":"External event - catering costs - (location)"
    },
    {
        "Directorate":"Directorate For External Affairs",
        "Merchant Name":"New Lsf Montpellier",
        "Merchant Category Description":"Schools & educational svc-not elsewhere classified",
        "Transaction Date":"04\/03\/2021",
        "Transaction Amount":"£981.69",
        "Final Expense Description":"External training course - fees"
    },
    {
        "Directorate":"Directorate For External Affairs",
        "Merchant Name":"Sumup Holleville",
        "Merchant Category Description":"Schools & educational svc-not elsewhere classified",
        "Transaction Date":"04\/03\/2021",
        "Transaction Amount":"£1,509.13",
        "Final Expense Description":"External training course - fees"
    },
    {
        "Directorate":"Directorate For External Affairs",
        "Merchant Name":"WWW.ADDISONLEE.COM",
        "Merchant Category Description":"Limousines and taxicabs",
        "Transaction Date":"05\/03\/2021",
        "Transaction Amount":"£503.41",
        "Final Expense Description":"Travel costs - limousine hire or Travel costs - car hire"
    },
    {
        "Directorate":"Directorate For Fair Work, Employability & Skills",
        "Merchant Name":"Eb Making Sense Of Se",
        "Merchant Category Description":"Business services-not elsewhere classified",
        "Transaction Date":"08\/03\/2021",
        "Transaction Amount":"£720.00",
        "Final Expense Description":"External event - fees"
    },
    {
        "Directorate":"Directorate For Financial Management",
        "Merchant Name":"Adobe Creative Cloud",
        "Merchant Category Description":"Computer software stores",
        "Transaction Date":"30\/03\/2021",
        "Transaction Amount":"£596.33",
        "Final Expense Description":"External training course - fees"
    },
    {
        "Directorate":"Directorate For Health Performance & Delivery",
        "Merchant Name":"Surveymonkey",
        "Merchant Category Description":"Comp programing,data prcsng,intgrtd sys dsgn srvs",
        "Transaction Date":"27\/03\/2021",
        "Transaction Amount":"£900.00",
        "Final Expense Description":"Professional licence - fees OR Professional licence - renewal"
    },
    {
        "Directorate":"Directorate For Health Workforce & Leadership",
        "Merchant Name":"WWW.COVENTRYUNIVERSITY",
        "Merchant Category Description":"Colleges, universities,professional schools & junior colleges",
        "Transaction Date":"16\/03\/2021",
        "Transaction Amount":"£500.00",
        "Final Expense Description":"External training course - fees"
    },
    {
        "Directorate":"Directorate For Health Workforce & Leadership",
        "Merchant Name":"The Keil Centre Ltd",
        "Merchant Category Description":"Doctors, (not elsewhere classified)",
        "Transaction Date":"16\/03\/2021",
        "Transaction Amount":"£2,160.00",
        "Final Expense Description":"External training course - fees"
    },
    {
        "Directorate":"Directorate For Housing & Social Justice",
        "Merchant Name":"Third Sector Lab",
        "Merchant Category Description":"Computer software stores",
        "Transaction Date":"16\/03\/2021",
        "Transaction Amount":"£900.00",
        "Final Expense Description":"Specialist softwares OR Specialist software - renewal"
    },
    {
        "Directorate":"Directorate For Housing & Social Justice",
        "Merchant Name":"C I H",
        "Merchant Category Description":"Associations-civic, social, and fraternal",
        "Transaction Date":"11\/03\/2021",
        "Transaction Amount":"£4,000.00",
        "Final Expense Description":"grant sponsor"
    },
    {
        "Directorate":"Directorate For Internal Audit And Assurance",
        "Merchant Name":"Iia Cia Lrng Systms",
        "Merchant Category Description":"Schools, elementary and secondary",
        "Transaction Date":"15\/03\/2021",
        "Transaction Amount":"£1,188.05",
        "Final Expense Description":"Specialist softwares OR Specialist software - renewal"
    },
    {
        "Directorate":"Directorate For International Trade & Investment",
        "Merchant Name":"Civil Service College",
        "Merchant Category Description":"Schools & educational svc-not elsewhere classified",
        "Transaction Date":"11\/03\/2021",
        "Transaction Amount":"£780.00",
        "Final Expense Description":"External training course - fees"
    },
    {
        "Directorate":"Directorate For Learning",
        "Merchant Name":"Msft E0800E036D",
        "Merchant Category Description":"Computers, computer peripheral equipment, software",
        "Transaction Date":"18\/03\/2021",
        "Transaction Amount":"£501.60",
        "Final Expense Description":"Professional subscription - fees"
    },
    {
        "Directorate":"Directorate For Learning",
        "Merchant Name":"Msft E0500Dvyv1",
        "Merchant Category Description":"Computers, computer peripheral equipment, software",
        "Transaction Date":"07\/03\/2021",
        "Transaction Amount":"£592.80",
        "Final Expense Description":"Professional subscription - fees"
    },
    {
        "Directorate":"Directorate For Legal Services",
        "Merchant Name":"Zoom.Us 888-799-9666",
        "Merchant Category Description":"Telecom incl prepaid\/recurring phone svcs",
        "Transaction Date":"25\/03\/2021",
        "Transaction Amount":"£1,918.80",
        "Final Expense Description":"Professional subscription - fees"
    },
    {
        "Directorate":"Directorate For Local Government & Communities",
        "Merchant Name":"Zoom.Gbp",
        "Merchant Category Description":"Direct marketing-continuity\/subscription merchants",
        "Transaction Date":"05\/03\/2021",
        "Transaction Amount":"£1,918.80",
        "Final Expense Description":"Professional subscription - fees"
    },
    {
        "Directorate":"Directorate For Local Government & Communities",
        "Merchant Name":"Amznmktplace Amazon.Co",
        "Merchant Category Description":"Miscellaneous and specialty retail stores",
        "Transaction Date":"06\/03\/2021",
        "Transaction Amount":"£1,749.99",
        "Final Expense Description":"IT hardware - specialist equipment"
    },
    {
        "Directorate":"Directorate For Local Government & Communities",
        "Merchant Name":"Storiesonboard",
        "Merchant Category Description":"Computers, computer peripheral equipment, software",
        "Transaction Date":"25\/03\/2021",
        "Transaction Amount":"£569.14",
        "Final Expense Description":"Professional subscription - fees"
    },
    {
        "Directorate":"Directorate For Local Government & Communities",
        "Merchant Name":"Rtpi",
        "Merchant Category Description":"Organizations, charitable and social services",
        "Transaction Date":"17\/03\/2021",
        "Transaction Amount":"£3,600.00",
        "Final Expense Description":"Professional membership - fees OR Professional subscription - fees"
    },
    {
        "Directorate":"Directorate For Local Government & Communities",
        "Merchant Name":"Msft E0700Dutr5",
        "Merchant Category Description":"Computers, computer peripheral equipment, software",
        "Transaction Date":"13\/03\/2021",
        "Transaction Amount":"£4,752.07",
        "Final Expense Description":"Professional membership - fees OR Professional subscription - fees"
    },
    {
        "Directorate":"Directorate For Marine Scotland",
        "Merchant Name":"Lochinver Holiday Lod",
        "Merchant Category Description":"Lodging-hotels,motels,resorts-not classified",
        "Transaction Date":"01\/03\/2021",
        "Transaction Amount":"£1,400.00",
        "Final Expense Description":"Travel costs - accomodation"
    },
    {
        "Directorate":"Directorate For Marine Scotland",
        "Merchant Name":"Sq The Barefoot Think",
        "Merchant Category Description":"Business services-not elsewhere classified",
        "Transaction Date":"08\/03\/2021",
        "Transaction Amount":"£3,600.00",
        "Final Expense Description":"External training course - fees"
    },
    {
        "Directorate":"Directorate For Marine Scotland",
        "Merchant Name":"WWW.F1TRAIN.CO.UK",
        "Merchant Category Description":"Schools & educational svc-not elsewhere classified",
        "Transaction Date":"08\/03\/2021",
        "Transaction Amount":"£955.20",
        "Final Expense Description":"External training course - fees"
    },
    {
        "Directorate":"Directorate For Marine Scotland",
        "Merchant Name":"Gael Force Marine-Vt",
        "Merchant Category Description":"Marinas, marine service\/supplies",
        "Transaction Date":"11\/03\/2021",
        "Transaction Amount":"£883.82",
        "Final Expense Description":"Vessel engineering equipment - maintenance"
    },
    {
        "Directorate":"Directorate For Marine Scotland",
        "Merchant Name":"Waverley Cutting",
        "Merchant Category Description":"Hardware stores",
        "Transaction Date":"26\/02\/2021",
        "Transaction Amount":"£1,679.04",
        "Final Expense Description":"Vessel engineering equipment"
    },
    {
        "Directorate":"Directorate For Marine Scotland",
        "Merchant Name":"Acornindust",
        "Merchant Category Description":"Industrial supplies not elsewhere classified",
        "Transaction Date":"19\/03\/2021",
        "Transaction Amount":"£597.80",
        "Final Expense Description":"Vessel engineering equipment"
    },
    {
        "Directorate":"Directorate For Marine Scotland",
        "Merchant Name":"Tapflo (Uk) Ltd",
        "Merchant Category Description":"Industrial supplies not elsewhere classified",
        "Transaction Date":"24\/03\/2021",
        "Transaction Amount":"£622.00",
        "Final Expense Description":"Vessel engineering equipment"
    },
    {
        "Directorate":"Directorate For Marine Scotland",
        "Merchant Name":"Hp Inc Hp.Com Store Uk",
        "Merchant Category Description":"Electronic sales",
        "Transaction Date":"25\/03\/2021",
        "Transaction Amount":"£1,251.60",
        "Final Expense Description":"Specialist IT equipment"
    },
    {
        "Directorate":"Directorate For Marine Scotland",
        "Merchant Name":"Amznmktplace",
        "Merchant Category Description":"Miscellaneous and specialty retail stores",
        "Transaction Date":"19\/03\/2021",
        "Transaction Amount":"£772.86",
        "Final Expense Description":"Specialist IT equipment"
    },
    {
        "Directorate":"Directorate For Marine Scotland",
        "Merchant Name":"Alibaba.Com",
        "Merchant Category Description":"Wholesale clubs",
        "Transaction Date":"01\/03\/2021",
        "Transaction Amount":"£817.92",
        "Final Expense Description":"Photographic equipment"
    },
    {
        "Directorate":"Directorate For Marine Scotland",
        "Merchant Name":"Swann Communications",
        "Merchant Category Description":"Camera and photographic supply stores",
        "Transaction Date":"01\/03\/2021",
        "Transaction Amount":"£1,099.99",
        "Final Expense Description":"Photographic equipment"
    },
    {
        "Directorate":"Directorate For Marine Scotland",
        "Merchant Name":"Mo & Co",
        "Merchant Category Description":"Men's and women's clothing stores",
        "Transaction Date":"17\/03\/2021",
        "Transaction Amount":"£1,860.00",
        "Final Expense Description":"Vessel safety equipment - clothing"
    },
    {
        "Directorate":"Directorate For Marine Scotland",
        "Merchant Name":"Macqueen Bros",
        "Merchant Category Description":"Freight carrier,trucking-lcl\/lng dist, mvg\/storage",
        "Transaction Date":"08\/03\/2021",
        "Transaction Amount":"£782.15",
        "Final Expense Description":"Storage fees"
    },
    {
        "Directorate":"Directorate For Marine Scotland",
        "Merchant Name":"Amznmktplace Amazon.Co",
        "Merchant Category Description":"Miscellaneous and specialty retail stores",
        "Transaction Date":"28\/02\/2021",
        "Transaction Amount":"£520.19",
        "Final Expense Description":"Vessel engineering equipment"
    },
    {
        "Directorate":"Directorate For Marine Scotland",
        "Merchant Name":"Northern Diver (Intnl)",
        "Merchant Category Description":"Sporting goods stores",
        "Transaction Date":"24\/03\/2021",
        "Transaction Amount":"£632.40",
        "Final Expense Description":"Vessel safety equipment - clothing"
    },
    {
        "Directorate":"Directorate For Marine Scotland",
        "Merchant Name":"Simon Safety And Lifti",
        "Merchant Category Description":"Dental\/lab\/med\/ophthalmic hosp equip & supplies",
        "Transaction Date":"24\/03\/2021",
        "Transaction Amount":"£1,040.40",
        "Final Expense Description":"Safety clothing - coastal operation"
    },
    {
        "Directorate":"Directorate For Marine Scotland",
        "Merchant Name":"Biomerieux",
        "Merchant Category Description":"Dental\/lab\/med\/ophthalmic hosp equip & supplies",
        "Transaction Date":"23\/03\/2021",
        "Transaction Amount":"£736.39",
        "Final Expense Description":"Vessel equipment OR Vessel scientific equipment"
    },
    {
        "Directorate":"Directorate For Marine Scotland",
        "Merchant Name":"Www.Rhodesandscholes.C",
        "Merchant Category Description":"Office and commercial furniture",
        "Transaction Date":"22\/03\/2021",
        "Transaction Amount":"£630.00",
        "Final Expense Description":"Vessel engineering equipment"
    },
    {
        "Directorate":"Directorate For Marine Scotland",
        "Merchant Name":"Gtvisionltd",
        "Merchant Category Description":"Dental\/lab\/med\/ophthalmic hosp equip & supplies",
        "Transaction Date":"19\/03\/2021",
        "Transaction Amount":"£1,497.55",
        "Final Expense Description":"Vessel equipment OR Vessel scientific equipment"
    },
    {
        "Directorate":"Directorate For Marine Scotland",
        "Merchant Name":"WWW.UK.INSIGHT.COM",
        "Merchant Category Description":"Direct marketing-catalog merchants",
        "Transaction Date":"19\/03\/2021",
        "Transaction Amount":"£560.71",
        "Final Expense Description":"Vessel food stores"
    },
    {
        "Directorate":"Directorate For Marine Scotland",
        "Merchant Name":"George Anderson & Son",
        "Merchant Category Description":"Grocery stores, supermarkets",
        "Transaction Date":"18\/03\/2021",
        "Transaction Amount":"£508.29",
        "Final Expense Description":"Vessel equipment OR Vessel scientific equipment"
    },
    {
        "Directorate":"Directorate For Marine Scotland",
        "Merchant Name":"WWW.UK.INSIGHT.COM",
        "Merchant Category Description":"Direct marketing-catalog merchants",
        "Transaction Date":"25\/02\/2021",
        "Transaction Amount":"£2,738.88",
        "Final Expense Description":"Vessel equipment OR Vessel scientific equipment"
    },
    {
        "Directorate":"Directorate For Marine Scotland",
        "Merchant Name":"Elsevier Inc.",
        "Merchant Category Description":"Books,periodicals and newspapers",
        "Transaction Date":"24\/03\/2021",
        "Transaction Amount":"£1,180.00",
        "Final Expense Description":"Publication - fees"
    },
    {
        "Directorate":"Directorate For Marine Scotland",
        "Merchant Name":"Gemini Data Loggers (U",
        "Merchant Category Description":"Household appliance stores",
        "Transaction Date":"16\/03\/2021",
        "Transaction Amount":"£616.74",
        "Final Expense Description":"Vessel engineering equipment"
    },
    {
        "Directorate":"Directorate For Marine Scotland",
        "Merchant Name":"Fluid Pumps Ltd",
        "Merchant Category Description":"Miscellaneous and specialty retail stores",
        "Transaction Date":"26\/02\/2021",
        "Transaction Amount":"£947.32",
        "Final Expense Description":"Vessel engineering equipment"
    },
    {
        "Directorate":"Directorate For Marine Scotland",
        "Merchant Name":"Rs Components",
        "Merchant Category Description":"Electrical parts and equipment",
        "Transaction Date":"25\/02\/2021",
        "Transaction Amount":"£1,231.38",
        "Final Expense Description":"Vessel equipment OR Vessel scientific equipment"
    },
    {
        "Directorate":"Directorate For Marine Scotland",
        "Merchant Name":"Pizza Equipment",
        "Merchant Category Description":"Equip, furniture, home furnshngs strs (excpt appl)",
        "Transaction Date":"26\/02\/2021",
        "Transaction Amount":"£1,645.00",
        "Final Expense Description":"Vessel engineering spares"
    },
    {
        "Directorate":"Directorate For Marine Scotland",
        "Merchant Name":"Esslab",
        "Merchant Category Description":"Dental\/lab\/med\/ophthalmic hosp equip & supplies",
        "Transaction Date":"22\/03\/2021",
        "Transaction Amount":"£974.09",
        "Final Expense Description":"Vessel equipment OR Vessel scientific equipment"
    },
    {
        "Directorate":"Directorate For Marine Scotland",
        "Merchant Name":"Varitech System",
        "Merchant Category Description":"Cleaning and maintenance, janitorial services",
        "Transaction Date":"23\/03\/2021",
        "Transaction Amount":"£2,205.84",
        "Final Expense Description":"Vessel safety equipment"
    },
    {
        "Directorate":"Directorate For Marine Scotland",
        "Merchant Name":"Bm Steel",
        "Merchant Category Description":"Architectural, engineering, and surveying services",
        "Transaction Date":"30\/03\/2021",
        "Transaction Amount":"£606.00",
        "Final Expense Description":"Vessel engineering spares"
    },
    {
        "Directorate":"Directorate For Marine Scotland",
        "Merchant Name":"Dell Products",
        "Merchant Category Description":"Computers, computer peripheral equipment, software",
        "Transaction Date":"23\/03\/2021",
        "Transaction Amount":"£4,470.44",
        "Final Expense Description":"IT Hardware - specialist equipment"
    },
    {
        "Directorate":"Directorate For Marine Scotland",
        "Merchant Name":"Migrate Technology Ltd",
        "Merchant Category Description":"Business services-not elsewhere classified",
        "Transaction Date":"19\/03\/2021",
        "Transaction Amount":"£4,811.98",
        "Final Expense Description":"Vessel equipment OR Vessel scientific equipment"
    },
    {
        "Directorate":"Directorate For Marine Scotland",
        "Merchant Name":"Gsproducts.Co.Uk",
        "Merchant Category Description":"Miscellaneous and specialty retail stores",
        "Transaction Date":"08\/03\/2021",
        "Transaction Amount":"£885.59",
        "Final Expense Description":"Vessel engineering spares"
    },
    {
        "Directorate":"Directorate For Marine Scotland",
        "Merchant Name":"Dell Products",
        "Merchant Category Description":"Computers, computer peripheral equipment, software",
        "Transaction Date":"05\/03\/2021",
        "Transaction Amount":"£4,759.04",
        "Final Expense Description":"IT hardware - specialist equipment"
    },
    {
        "Directorate":"Directorate For Marine Scotland",
        "Merchant Name":"Reader Options Limited",
        "Merchant Category Description":"Contractors,special trade-not elsewhere classified",
        "Transaction Date":"23\/03\/2021",
        "Transaction Amount":"£1,714.32",
        "Final Expense Description":"Vessel equipment OR Vessel scientific equipment"
    },
    {
        "Directorate":"Directorate For Marine Scotland",
        "Merchant Name":"Varitech System",
        "Merchant Category Description":"Cleaning and maintenance, janitorial services",
        "Transaction Date":"23\/03\/2021",
        "Transaction Amount":"£2,205.84",
        "Final Expense Description":"Vessel safety equipment"
    },
    {
        "Directorate":"Directorate For Marine Scotland",
        "Merchant Name":"Indespension",
        "Merchant Category Description":"Camper dealers, recreational and utility trailers",
        "Transaction Date":"22\/03\/2021",
        "Transaction Amount":"£2,061.00",
        "Final Expense Description":"Vessel engineering equipment - maintenance"
    },
    {
        "Directorate":"Directorate For Marine Scotland",
        "Merchant Name":"Frontline Safety (Uk)",
        "Merchant Category Description":"Business services-not elsewhere classified",
        "Transaction Date":"04\/03\/2021",
        "Transaction Amount":"£2,489.14",
        "Final Expense Description":"Vessel engineering equipment - maintenance"
    },
    {
        "Directorate":"Directorate For Marine Scotland",
        "Merchant Name":"Hota",
        "Merchant Category Description":"Schools & educational svc-not elsewhere classified",
        "Transaction Date":"09\/03\/2021",
        "Transaction Amount":"£626.40",
        "Final Expense Description":"External training course - fees"
    },
    {
        "Directorate":"Directorate For Marine Scotland",
        "Merchant Name":"Chartco Limited Pbl",
        "Merchant Category Description":"Marinas, marine service\/supplies",
        "Transaction Date":"03\/03\/2021",
        "Transaction Amount":"£4,927.33",
        "Final Expense Description":"Professional subscription - fees"
    },
    {
        "Directorate":"Directorate For People",
        "Merchant Name":"Posturite Ltd",
        "Merchant Category Description":"Business services-not elsewhere classified",
        "Transaction Date":"11\/03\/2021",
        "Transaction Amount":"£919.08",
        "Final Expense Description":"Office equipment"
    },
    {
        "Directorate":"Directorate For People",
        "Merchant Name":"Adobe.Com",
        "Merchant Category Description":"Digital goods software applications",
        "Transaction Date":"29\/03\/2021",
        "Transaction Amount":"£596.33",
        "Final Expense Description":"Professional subscription - fees"
    },
    {
        "Directorate":"Directorate For People",
        "Merchant Name":"Institute Of Student E",
        "Merchant Category Description":"Employment agencies, temporary help services",
        "Transaction Date":"09\/03\/2021",
        "Transaction Amount":"£1,020.00",
        "Final Expense Description":"Professional membership - fees OR Professional subscription - fees"
    },
    {
        "Directorate":"Directorate For Population Health",
        "Merchant Name":"Isee Systems Inc",
        "Merchant Category Description":"Computer software stores",
        "Transaction Date":"04\/03\/2021",
        "Transaction Amount":"£4,879.68",
        "Final Expense Description":"Professional licence - fees OR Professional licence - renewal"
    },
    {
        "Directorate":"Directorate For Population Health",
        "Merchant Name":"Isee Systems Inc",
        "Merchant Category Description":"Computer software stores",
        "Transaction Date":"03\/03\/2021",
        "Transaction Amount":"£4,901.00",
        "Final Expense Description":"Specialist softwares OR Specialist software - renewal"
    },
    {
        "Directorate":"Directorate For Safer Communities",
        "Merchant Name":"Hand Lock",
        "Merchant Category Description":"Artist supply stores, craft shops",
        "Transaction Date":"26\/03\/2021",
        "Transaction Amount":"£902.30",
        "Final Expense Description":"Personal protective equipment OR Specialist protective clothing"
    },
    {
        "Directorate":"Directorate For Social Security",
        "Merchant Name":"Elite Training",
        "Merchant Category Description":"Comp programing,data prcsng,intgrtd sys dsgn srvs",
        "Transaction Date":"30\/03\/2021",
        "Transaction Amount":"£1,790.00",
        "Final Expense Description":"External training course - fees"
    },
    {
        "Directorate":"Directorate For Social Security",
        "Merchant Name":"WWW.QA.COM",
        "Merchant Category Description":"Schools & educational svc-not elsewhere classified",
        "Transaction Date":"10\/03\/2021",
        "Transaction Amount":"£18,000.00",
        "Final Expense Description":"Professional Licenses"
    },
    {
        "Directorate":"Directorate For Social Security",
        "Merchant Name":"WWW.QA.COM",
        "Merchant Category Description":"Schools & educational svc-not elsewhere classified",
        "Transaction Date":"08\/03\/2021",
        "Transaction Amount":"£18,000.00",
        "Final Expense Description":"Professional Licenses"
    },
    {
        "Directorate":"Directorate For Social Security",
        "Merchant Name":"Slack T6Ssmjn6T",
        "Merchant Category Description":"Computer software stores",
        "Transaction Date":"05\/03\/2021",
        "Transaction Amount":"£3,969.89",
        "Final Expense Description":"Professional Subscription - Renewal Fees"
    },
    {
        "Directorate":"Directorate For Social Security",
        "Merchant Name":"Parlicentre.Org",
        "Merchant Category Description":"Organizations, membership-not elsewhere classified",
        "Transaction Date":"10\/03\/2021",
        "Transaction Amount":"£684.00",
        "Final Expense Description":"External training course - fees"
    },
    {
        "Directorate":"Directorate For Social Security",
        "Merchant Name":"Premiere Conferencing",
        "Merchant Category Description":"Business services-not elsewhere classified",
        "Transaction Date":"18\/03\/2021",
        "Transaction Amount":"£2,205.40",
        "Final Expense Description":"External Services Support"
    },
    {
        "Directorate":"Directorate For Taxation & Fiscal Sustainability",
        "Merchant Name":"Knowledgetrain.Co.Uk",
        "Merchant Category Description":"Schools & educational svc-not elsewhere classified",
        "Transaction Date":"18\/03\/2021",
        "Transaction Amount":"£1,078.80",
        "Final Expense Description":"External training course - fees"
    },
    {
        "Directorate":"Scottish Procurement & Property Directorate",
        "Merchant Name":"WWW.RSS.ORG.UK",
        "Merchant Category Description":"Business services-not elsewhere classified",
        "Transaction Date":"25\/03\/2021",
        "Transaction Amount":"£733.20",
        "Final Expense Description":"External training course - fees"
    },
    {
        "Directorate":"Scottish Procurement & Property Directorate",
        "Merchant Name":"Payoneer.Com",
        "Merchant Category Description":"Business services-not elsewhere classified",
        "Transaction Date":"25\/03\/2021",
        "Transaction Amount":"£9,211.50",
        "Final Expense Description":"External training course - fees"
    },
    {
        "Directorate":"Scottish Procurement & Property Directorate",
        "Merchant Name":"Project Mgmt Institute",
        "Merchant Category Description":"Schools & educational svc-not elsewhere classified",
        "Transaction Date":"16\/03\/2021",
        "Transaction Amount":"£5,616.27",
        "Final Expense Description":"Professional membership - fees OR Professional subscription - fees"
    },
    {
        "Directorate":"Scottish Procurement & Property Directorate",
        "Merchant Name":"Adobe Creative Cloud",
        "Merchant Category Description":"Computer software stores",
        "Transaction Date":"11\/03\/2021",
        "Transaction Amount":"£849.60",
        "Final Expense Description":"Specialist softwares OR Specialist software - renewal"
    },
    {
        "Directorate":"Scottish Procurement & Property Directorate",
        "Merchant Name":"Amznmktplace",
        "Merchant Category Description":"Miscellaneous and specialty retail stores",
        "Transaction Date":"05\/03\/2021",
        "Transaction Amount":"£2,698.00",
        "Final Expense Description":"IT hardware - specialist equipment"
    },
    {
        "Directorate":"Scottish Procurement & Property Directorate",
        "Merchant Name":"Igpp Ltd",
        "Merchant Category Description":"Other services (not elsewhere classified)",
        "Transaction Date":"03\/03\/2021",
        "Transaction Amount":"£1,416.00",
        "Final Expense Description":"External event - fees"
    }
]